{"kind":"youtube#playlistItemListResponse","etag":"60NDubWA6mv8DLdXoKVSVe4io6M","nextPageToken":"CB4QAA","items":[{"kind":"youtube#playlistItem","etag":"nSi6uP-_q-ECXN12iCmgymZWR9U","id":"UExhMUYyZGRHeWFfODdISjcydl9JZ0tVVE5MSVhTTWZ2Qi4zQTkyMjEwN0U0QkU3RDg5","snippet":{"publishedAt":"2021-02-22T17:26:14Z","channelId":"UCSMOQeBJ2RAnuFungnQOxLg","title":"CYCLES ❤️ GEOMETRY NODES | Blender.Today LIVE #140","description":"It's a match!\n\nBLENDER TODAY #140 - 22-02-2021\nSergey coding LIVE https://www.youtube.com/watch?v=ZUoTCONlcu4 \nRender Module Update https://code.blender.org/2021/02/render-modules-update/\nCreating Stylized Animals -- An Overview With Blender Studio Artist Julien Kaspar https://www.youtube.com/watch?v=mCr0SQ7hhzs \n\nUI\nAdding node groups via drag & drop (e.g. from Asset Browser) https://developer.blender.org/rB604e61d81d6326e665de6ec81dca2619e2cd5dbc\nUI: FModifier layout updates, drag and drop https://developer.blender.org/D7997 \nUI: fuzzy search in collection search https://developer.blender.org/D10446 \n\nGEOMETRY NODES\nGeometry Nodes: Add string input node https://developer.blender.org/rBa961a2189cb38ffb368d6781aa57177bfefe0e36\nGeometry Nodes: Add simple subdivision surface node https://developer.blender.org/D10409 \nGeometry Nodes: Node error messages https://developer.blender.org/D10290\nGeometry Nodes: realize instances before passing geometry to constructive mesh modifier https://developer.blender.org/rB96da8e9ca302b8d879744318c5ad12c64a5b3c2c \nGeometry Nodes: convert point cloud to mesh vertices for modifiers https://developer.blender.org/rB999abee874bd7d69f6a40c27969598869799e8dc  \nGeometry Nodes: support accessing vertex colors https://developer.blender.org/rBe3f0b6d5cbe5d34ac43568090c52a84dc51e579e \nGeometry Nodes: Expose material index attribute https://developer.blender.org/rB53bf04f2844b64cd9f79bedd047eac9690f872e3 \nCycles: support accessing custom mesh attributes https://developer.blender.org/D10210 \nGeometry Nodes: Use corner domain for density map in Point Distribute node. https://developer.blender.org/D10461 \n\nWORKBENCH\nWorkbench: Improve AntiAliasing sampling https://developer.blender.org/rB36814ddc94b56a66675b854bc0d7485828ddcd31 \n\nOVERRIDES\nLibOverride: Add support for rotation mode of PoseBones. https://developer.blender.org/rB82ade44299083e86acbaafbcb21ac350d861881d \n\nASSETS\nAssets: Remove appended asset when dropping operation fails https://developer.blender.org/rBe81fca1ed38ea447a1023dae3841f8980def28e4 \n\nPYTHON\nPython: Add to_curve method to the object API https://developer.blender.org/D10354 \nmacOS\nmacOS: add Embree, OpenImageDenoise and sse2neon libraries for ARM https://developer.blender.org/rBae370e292af2f7092db02301e9deb6dd9d7a1441 \n\nADD-ONS\nAfter Effects export: add solid and image plane export https://developer.blender.org/rBACa140f066ac99e1860af38080f008507029a34706 \n\nThumbnail artwork by James Redmond https://www.blender.org/download/demo-files/#geometry-nodes \n\nSupport core Blender development - https://fund.blender.org\n\n--\n\nBlenderToday Links:\n* Chat: https://blender.chat/channel/today\n* Community: http://blender.today\n* Twitter: https://twitter.com/BlenderToday\n* YouTube - https://www.youtube.com/BlenderCommunity\n\n--\n\nPablo Vazquez Links: \n* Superpeer - https://superpeer.com/pablovazquez\n* Instagram - https://instagram.com/pablovazquez.art\n* Twitter - https://twitter.com/pablovazquez_\n* YouTube - https://www.youtube.com/PabloVazquez\n* ArtStation - https://artstation.com/pablovazquez\n\n#BlenderToday #b3d\n\nMusic by Thaehan https://www.youtube.com/watch?v=LkphuCqnvmo","thumbnails":{"default":{"url":"https://i.ytimg.com/vi/lMWVZKCbYRc/default.jpg","width":120,"height":90},"medium":{"url":"https://i.ytimg.com/vi/lMWVZKCbYRc/mqdefault.jpg","width":320,"height":180},"high":{"url":"https://i.ytimg.com/vi/lMWVZKCbYRc/hqdefault.jpg","width":480,"height":360},"standard":{"url":"https://i.ytimg.com/vi/lMWVZKCbYRc/sddefault.jpg","width":640,"height":480},"maxres":{"url":"https://i.ytimg.com/vi/lMWVZKCbYRc/maxresdefault.jpg","width":1280,"height":720}},"channelTitle":"Blender","playlistId":"PLa1F2ddGya_87HJ72v_IgKUTNLIXSMfvB","position":0,"resourceId":{"kind":"youtube#video","videoId":"lMWVZKCbYRc"},"videoOwnerChannelTitle":"Blender","videoOwnerChannelId":"UCSMOQeBJ2RAnuFungnQOxLg"},"contentDetails":{"videoId":"lMWVZKCbYRc","videoPublishedAt":"2021-02-22T17:25:24Z"},"status":{"privacyStatus":"public"}},{"kind":"youtube#playlistItem","etag":"IqAgIC9HsjSyyHNaInV5xx7l-Sg","id":"UExhMUYyZGRHeWFfODdISjcydl9JZ0tVVE5MSVhTTWZ2Qi5DNzNDRDE1NzhGODQzODI2","snippet":{"publishedAt":"2021-02-01T15:50:48Z","channelId":"UCSMOQeBJ2RAnuFungnQOxLg","title":"Geometry Nodes and the Melting Iceberg #137 | Blender.Today LIVE","description":"SPECIAL EPISODE! Dalai Felinto will talk about how the Geometry Nodes project introduced a new way of working at Blender.\n\n--\n\nBlenderToday Links:\n* Chat: https://blender.chat/channel/today\n* Community: http://blender.today\n* Twitter: https://twitter.com/BlenderToday\n* YouTube - https://www.youtube.com/BlenderCommunity\n\n--\n\nPablo Vazquez Links: \n* Superpeer - https://superpeer.com/pablovazquez\n* Instagram - https://instagram.com/pablovazquez.art\n* Twitter - https://twitter.com/pablovazquez_\n* YouTube - https://www.youtube.com/PabloVazquez\n* ArtStation - https://artstation.com/pablovazquez\n\nSupport core Blender development - https://fund.blender.org\n\n#BlenderToday #b3d\n\nMusic by Thaehan https://www.youtube.com/watch?v=LkphuCqnvmo","thumbnails":{"default":{"url":"https://i.ytimg.com/vi/m-B4QKxy-Bo/default.jpg","width":120,"height":90},"medium":{"url":"https://i.ytimg.com/vi/m-B4QKxy-Bo/mqdefault.jpg","width":320,"height":180},"high":{"url":"https://i.ytimg.com/vi/m-B4QKxy-Bo/hqdefault.jpg","width":480,"height":360},"standard":{"url":"https://i.ytimg.com/vi/m-B4QKxy-Bo/sddefault.jpg","width":640,"height":480},"maxres":{"url":"https://i.ytimg.com/vi/m-B4QKxy-Bo/maxresdefault.jpg","width":1280,"height":720}},"channelTitle":"Blender","playlistId":"PLa1F2ddGya_87HJ72v_IgKUTNLIXSMfvB","position":1,"resourceId":{"kind":"youtube#video","videoId":"m-B4QKxy-Bo"},"videoOwnerChannelTitle":"Blender","videoOwnerChannelId":"UCSMOQeBJ2RAnuFungnQOxLg"},"contentDetails":{"videoId":"m-B4QKxy-Bo","videoPublishedAt":"2021-02-01T17:14:42Z"},"status":{"privacyStatus":"public"}},{"kind":"youtube#playlistItem","etag":"7u_c-Mii7ZXeupl2TIoPARa95KY","id":"UExhMUYyZGRHeWFfODdISjcydl9JZ0tVVE5MSVhTTWZ2Qi5CNzAzQzRDMkI3QThEQzZB","snippet":{"publishedAt":"2021-02-01T02:12:22Z","channelId":"UCSMOQeBJ2RAnuFungnQOxLg","title":"SAMPLE TEXTURE NODE! #136 | Blender.Today LIVE","description":"ASSET BROWSER\nAsset Browser: Support dragging image assets into node editors https://developer.blender.org/rBdb15df0baaad0d7ddedbae86b76ebcb342b14616  \nAsset Browser: Support dragging mask assets into compositors https://developer.blender.org/rBb449da3a7d4836362a720a0072fad3e0a02f185a   \n\nUI\nUI: Object \"Make Links\" sub-menu overhaul https://developer.blender.org/rB685419d6bebfec1542ecbe8c3542baba88132604 \nUI: particle tool properties layout tweaks https://developer.blender.org/rBeb45e7be47f7ab0a37f869bf1d12e6cee10b24b8 \nUI: Transform Arrow Cursor Refactor https://developer.blender.org/D9668 \nUI: Viewport Navigate Gizmo Refactor https://developer.blender.org/D9744 \nUI: Gizmo Tooltip Positions https://developer.blender.org/D9793 \nUI: move 'Trace Image to Grease Pencil' to 'Convert' sub-menu https://developer.blender.org/rB5a1cef2e763f70230259433423cd33a644e46218 \n\nGEOMETRY NODES\n2.92 - Geometry Nodes - Object Info: option to apply obj transform to the geometry https://developer.blender.org/rB8b777ee6d69d4805c64756cf6a33db894160ce29 \nGeometry Nodes: initial support for volumes https://developer.blender.org/rB793547e7d1401ad545e0450b80c7bafd521c60e1 \nGeometry Nodes: new Attribute Sample Texture node https://developer.blender.org/rB425e706921a8f986921b8b9c429874fed98e9a10 \n\nCYCLES\nCycles: internal support for the concept of procedurals https://developer.blender.org/rB2e67191c861f2cb148f05af116114e7332b8e789 \nCycles: internal support for Alembic procedurals https://developer.blender.org/rBb64f0fab068169a7c379be728aae8994eb893b18 \n\nGPENCIL\nGPencil Tools: Add viewport timeline scrub feature https://developer.blender.org/rBA76fba3f84b6fdcc350d232eb740c0cd72ac9ffb7\nGPencil: New option to trace current frame https://developer.blender.org/rBe747c07156cce226dde25309b4346f8354103a24 \n\nVSE\nVSE: Inherit blend mode with single input effects https://developer.blender.org/rBd6bbcc4f666b257fed3e6f8ec468d0efff5b591f \n\n--\n\nBlenderToday Links:\n* Chat: https://blender.chat/channel/today\n* Community: http://blender.today\n* Twitter: https://twitter.com/BlenderToday\n* YouTube - https://www.youtube.com/BlenderCommunity\n\n--\n\nPablo Vazquez Links: \n* Superpeer - https://superpeer.com/pablovazquez\n* Instagram - https://instagram.com/pablovazquez.art\n* Twitter - https://twitter.com/pablovazquez_\n* YouTube - https://www.youtube.com/PabloVazquez\n* ArtStation - https://artstation.com/pablovazquez\n\nSupport core Blender development - https://fund.blender.org\n\n#BlenderToday #b3d","thumbnails":{"default":{"url":"https://i.ytimg.com/vi/6k2uqKt5etE/default.jpg","width":120,"height":90},"medium":{"url":"https://i.ytimg.com/vi/6k2uqKt5etE/mqdefault.jpg","width":320,"height":180},"high":{"url":"https://i.ytimg.com/vi/6k2uqKt5etE/hqdefault.jpg","width":480,"height":360},"standard":{"url":"https://i.ytimg.com/vi/6k2uqKt5etE/sddefault.jpg","width":640,"height":480},"maxres":{"url":"https://i.ytimg.com/vi/6k2uqKt5etE/maxresdefault.jpg","width":1280,"height":720}},"channelTitle":"Blender","playlistId":"PLa1F2ddGya_87HJ72v_IgKUTNLIXSMfvB","position":2,"resourceId":{"kind":"youtube#video","videoId":"6k2uqKt5etE"},"videoOwnerChannelTitle":"Blender","videoOwnerChannelId":"UCSMOQeBJ2RAnuFungnQOxLg"},"contentDetails":{"videoId":"6k2uqKt5etE","videoPublishedAt":"2021-01-25T17:33:28Z"},"status":{"privacyStatus":"public"}},{"kind":"youtube#playlistItem","etag":"Qh-t9mVWmsa6TL4Smqt0kLmXZVg","id":"UExhMUYyZGRHeWFfODdISjcydl9JZ0tVVE5MSVhTTWZ2Qi4xREVBMTg1ODg1M0JCQUE1","snippet":{"publishedAt":"2021-02-01T02:14:00Z","channelId":"UCSMOQeBJ2RAnuFungnQOxLg","title":"NODES GALORE #135 | Blender.Today LIVE","description":"BlenderToday Links:\n* Chat: https://blender.chat/channel/today\n* Community: http://blender.today\n* Twitter: https://twitter.com/BlenderToday\n* YouTube - https://www.youtube.com/BlenderCommunity\n\n--\n\nPablo Vazquez Links: \n* Instagram - https://instagram.com/pablovazquez.art\n* Twitter - https://twitter.com/pablovazquez_\n* YouTube - https://www.youtube.com/PabloVazquez\n* ArtStation - https://artstation.com/pablovazquez\n\nSupport core Blender development - https://fund.blender.org\n\n#BlenderToday #b3d","thumbnails":{"default":{"url":"https://i.ytimg.com/vi/x9otqZf10V0/default.jpg","width":120,"height":90},"medium":{"url":"https://i.ytimg.com/vi/x9otqZf10V0/mqdefault.jpg","width":320,"height":180},"high":{"url":"https://i.ytimg.com/vi/x9otqZf10V0/hqdefault.jpg","width":480,"height":360}},"channelTitle":"Blender","playlistId":"PLa1F2ddGya_87HJ72v_IgKUTNLIXSMfvB","position":3,"resourceId":{"kind":"youtube#video","videoId":"x9otqZf10V0"},"videoOwnerChannelTitle":"Blender","videoOwnerChannelId":"UCSMOQeBJ2RAnuFungnQOxLg"},"contentDetails":{"videoId":"x9otqZf10V0","videoPublishedAt":"2021-01-18T17:21:34Z"},"status":{"privacyStatus":"public"}},{"kind":"youtube#playlistItem","etag":"dWBgmGhfH3UWv1IyREHUOrU_o1Y","id":"UExhMUYyZGRHeWFfODdISjcydl9JZ0tVVE5MSVhTTWZ2Qi43MzBFRTZDMUM3OTY2RjQ4","snippet":{"publishedAt":"2021-02-01T02:14:00Z","channelId":"UCSMOQeBJ2RAnuFungnQOxLg","title":"VSE 2.0 #134 | Blender.Today LIVE","description":"BlenderToday Links:\n* Chat: https://blender.chat/channel/today\n* Community: http://blender.today\n* Twitter: https://twitter.com/BlenderToday\n* YouTube - https://www.youtube.com/BlenderCommunity\n\n--\n\nPablo Vazquez Links: \n* Instagram - https://instagram.com/pablovazquez.art\n* Twitter - https://twitter.com/pablovazquez_\n* YouTube - https://www.youtube.com/PabloVazquez\n* ArtStation - https://artstation.com/pablovazquez\n\nSupport core Blender development - https://fund.blender.org\n\n#BlenderToday #b3d","thumbnails":{"default":{"url":"https://i.ytimg.com/vi/Pd1d6KoUWMc/default.jpg","width":120,"height":90},"medium":{"url":"https://i.ytimg.com/vi/Pd1d6KoUWMc/mqdefault.jpg","width":320,"height":180},"high":{"url":"https://i.ytimg.com/vi/Pd1d6KoUWMc/hqdefault.jpg","width":480,"height":360},"standard":{"url":"https://i.ytimg.com/vi/Pd1d6KoUWMc/sddefault.jpg","width":640,"height":480},"maxres":{"url":"https://i.ytimg.com/vi/Pd1d6KoUWMc/maxresdefault.jpg","width":1280,"height":720}},"channelTitle":"Blender","playlistId":"PLa1F2ddGya_87HJ72v_IgKUTNLIXSMfvB","position":4,"resourceId":{"kind":"youtube#video","videoId":"Pd1d6KoUWMc"},"videoOwnerChannelTitle":"Blender","videoOwnerChannelId":"UCSMOQeBJ2RAnuFungnQOxLg"},"contentDetails":{"videoId":"Pd1d6KoUWMc","videoPublishedAt":"2021-01-11T17:55:05Z"},"status":{"privacyStatus":"public"}},{"kind":"youtube#playlistItem","etag":"YzUOAU27_6pnKwduLSAR3_A9ySQ","id":"UExhMUYyZGRHeWFfODdISjcydl9JZ0tVVE5MSVhTTWZ2Qi45QzM0OUZCRDUyMTgwREVG","snippet":{"publishedAt":"2021-01-04T15:46:47Z","channelId":"UCSMOQeBJ2RAnuFungnQOxLg","title":"BLENDER 2021 #133 | Blender.Today LIVE","description":"New year, new features!\n\n==\n\nBlenderToday Links:\n* Chat: https://blender.chat/channel/today\n* Community: http://blender.today\n* Twitter: https://twitter.com/BlenderToday\n* YouTube - https://www.youtube.com/BlenderCommunity\n\n--\n\nPablo Vazquez Links: \n* Instagram - https://instagram.com/pablovazquez.art\n* Twitter - https://twitter.com/pablovazquez_\n* YouTube - https://www.youtube.com/PabloVazquez\n* ArtStation - https://artstation.com/pablovazquez\n\nSupport core Blender development - https://fund.blender.org\n\n#BlenderToday #b3d","thumbnails":{"default":{"url":"https://i.ytimg.com/vi/Nlqjfj1lL5A/default.jpg","width":120,"height":90},"medium":{"url":"https://i.ytimg.com/vi/Nlqjfj1lL5A/mqdefault.jpg","width":320,"height":180},"high":{"url":"https://i.ytimg.com/vi/Nlqjfj1lL5A/hqdefault.jpg","width":480,"height":360},"standard":{"url":"https://i.ytimg.com/vi/Nlqjfj1lL5A/sddefault.jpg","width":640,"height":480},"maxres":{"url":"https://i.ytimg.com/vi/Nlqjfj1lL5A/maxresdefault.jpg","width":1280,"height":720}},"channelTitle":"Blender","playlistId":"PLa1F2ddGya_87HJ72v_IgKUTNLIXSMfvB","position":5,"resourceId":{"kind":"youtube#video","videoId":"Nlqjfj1lL5A"},"videoOwnerChannelTitle":"Blender","videoOwnerChannelId":"UCSMOQeBJ2RAnuFungnQOxLg"},"contentDetails":{"videoId":"Nlqjfj1lL5A","videoPublishedAt":"2021-01-04T17:23:53Z"},"status":{"privacyStatus":"public"}},{"kind":"youtube#playlistItem","etag":"jF1bzyK52uz5Q2a0XrXluVaxuTw","id":"UExhMUYyZGRHeWFfODdISjcydl9JZ0tVVE5MSVhTTWZ2Qi5DMkM0MjQ3OTgwQzBCMEZB","snippet":{"publishedAt":"2020-12-21T15:21:39Z","channelId":"UCSMOQeBJ2RAnuFungnQOxLg","title":"THIS IS THE END #132 | Blender.Today LIVE","description":"...of the year! Last episode of 2020, what a year. Tune in for updates on Asset Browser, Geometry Nodes, Video Sequencer, and more!\n\n==\n\nBlenderToday Links:\n* Chat: https://blender.chat/channel/today\n* Community: http://blender.today\n* Twitter: https://twitter.com/BlenderToday\n* YouTube - https://www.youtube.com/BlenderCommunity\n\n--\n\nPablo Vazquez Links: \n* Instagram - https://instagram.com/pablovazquez.art\n* Twitter - https://twitter.com/pablovazquez_\n* YouTube - https://www.youtube.com/PabloVazquez\n* ArtStation - https://artstation.com/pablovazquez\n\nSupport core Blender development - https://fund.blender.org\n\n#BlenderToday #b3d","thumbnails":{"default":{"url":"https://i.ytimg.com/vi/G-RENTMdgEo/default.jpg","width":120,"height":90},"medium":{"url":"https://i.ytimg.com/vi/G-RENTMdgEo/mqdefault.jpg","width":320,"height":180},"high":{"url":"https://i.ytimg.com/vi/G-RENTMdgEo/hqdefault.jpg","width":480,"height":360},"standard":{"url":"https://i.ytimg.com/vi/G-RENTMdgEo/sddefault.jpg","width":640,"height":480},"maxres":{"url":"https://i.ytimg.com/vi/G-RENTMdgEo/maxresdefault.jpg","width":1280,"height":720}},"channelTitle":"Blender","playlistId":"PLa1F2ddGya_87HJ72v_IgKUTNLIXSMfvB","position":6,"resourceId":{"kind":"youtube#video","videoId":"G-RENTMdgEo"},"videoOwnerChannelTitle":"Blender","videoOwnerChannelId":"UCSMOQeBJ2RAnuFungnQOxLg"},"contentDetails":{"videoId":"G-RENTMdgEo","videoPublishedAt":"2020-12-21T17:49:57Z"},"status":{"privacyStatus":"public"}},{"kind":"youtube#playlistItem","etag":"hJbFRGKi9l_vvjMknIm2wJlxoIw","id":"UExhMUYyZGRHeWFfODdISjcydl9JZ0tVVE5MSVhTTWZ2Qi5BRjY4NjdBRjA5RTdCMUMx","snippet":{"publishedAt":"2020-12-14T15:41:35Z","channelId":"UCSMOQeBJ2RAnuFungnQOxLg","title":"ASSET BROWSER? #131 | Blender.Today LIVE","description":"Are we there yet? Hashtag hype.\n\n==\n\nBlenderToday Links:\n* Chat: https://blender.chat/channel/today\n* Community: http://blender.today\n* Twitter: https://twitter.com/BlenderToday\n* YouTube - https://www.youtube.com/BlenderCommunity\n\n--\n\nPablo Vazquez Links: \n* Instagram - https://instagram.com/pablovazquez.art\n* Twitter - https://twitter.com/pablovazquez_\n* YouTube - https://www.youtube.com/PabloVazquez\n* ArtStation - https://artstation.com/pablovazquez\n\nSupport core Blender development - https://fund.blender.org\n\n#BlenderToday #b3d","thumbnails":{"default":{"url":"https://i.ytimg.com/vi/PW-p5ydrjKw/default.jpg","width":120,"height":90},"medium":{"url":"https://i.ytimg.com/vi/PW-p5ydrjKw/mqdefault.jpg","width":320,"height":180},"high":{"url":"https://i.ytimg.com/vi/PW-p5ydrjKw/hqdefault.jpg","width":480,"height":360},"standard":{"url":"https://i.ytimg.com/vi/PW-p5ydrjKw/sddefault.jpg","width":640,"height":480},"maxres":{"url":"https://i.ytimg.com/vi/PW-p5ydrjKw/maxresdefault.jpg","width":1280,"height":720}},"channelTitle":"Blender","playlistId":"PLa1F2ddGya_87HJ72v_IgKUTNLIXSMfvB","position":7,"resourceId":{"kind":"youtube#video","videoId":"PW-p5ydrjKw"},"videoOwnerChannelTitle":"Blender","videoOwnerChannelId":"UCSMOQeBJ2RAnuFungnQOxLg"},"contentDetails":{"videoId":"PW-p5ydrjKw","videoPublishedAt":"2020-12-14T17:20:08Z"},"status":{"privacyStatus":"public"}},{"kind":"youtube#playlistItem","etag":"dCy8G_7wVMab07ZyRvdjEh4yVA0","id":"UExhMUYyZGRHeWFfODdISjcydl9JZ0tVVE5MSVhTTWZ2Qi41RjU0OTVCQThDNUUwQzBD","snippet":{"publishedAt":"2020-12-07T13:44:38Z","channelId":"UCSMOQeBJ2RAnuFungnQOxLg","title":"NEW EEVEE PASSES #130 | Blender.Today LIVE","description":"Buckle up for a BlenderToday packed with updates! From Geometry Nodes, Eevee, sculpting, performance, and sooo much more!\n\n==\n\nBlenderToday Links:\n* Chat: https://blender.chat/channel/today\n* Community: http://blender.today\n* Twitter: https://twitter.com/BlenderToday\n* YouTube - https://www.youtube.com/BlenderCommunity\n\n--\n\nPablo Vazquez Links: \n* Instagram - https://instagram.com/pablovazquez.art\n* Twitter - https://twitter.com/pablovazquez_\n* YouTube - https://www.youtube.com/PabloVazquez\n* ArtStation - https://artstation.com/pablovazquez\n\nSupport core Blender development - https://fund.blender.org\n\n#BlenderToday #b3d","thumbnails":{"default":{"url":"https://i.ytimg.com/vi/cZP87Bd3HLI/default.jpg","width":120,"height":90},"medium":{"url":"https://i.ytimg.com/vi/cZP87Bd3HLI/mqdefault.jpg","width":320,"height":180},"high":{"url":"https://i.ytimg.com/vi/cZP87Bd3HLI/hqdefault.jpg","width":480,"height":360}},"channelTitle":"Blender","playlistId":"PLa1F2ddGya_87HJ72v_IgKUTNLIXSMfvB","position":8,"resourceId":{"kind":"youtube#video","videoId":"cZP87Bd3HLI"},"videoOwnerChannelTitle":"Blender","videoOwnerChannelId":"UCSMOQeBJ2RAnuFungnQOxLg"},"contentDetails":{"videoId":"cZP87Bd3HLI","videoPublishedAt":"2020-12-07T17:28:26Z"},"status":{"privacyStatus":"public"}},{"kind":"youtube#playlistItem","etag":"CUPxP839_PuE0O7DcNJJHH-fids","id":"UExhMUYyZGRHeWFfODdISjcydl9JZ0tVVE5MSVhTTWZ2Qi5EREU0QjZERDMzRDBGNTMz","snippet":{"publishedAt":"2020-11-30T12:23:05Z","channelId":"UCSMOQeBJ2RAnuFungnQOxLg","title":"HAIR for AAA GAMES #129 | Blender.Today LIVE","description":"Daniel Bystedt is visiting us again! This time to show how hair-grooming is done for AAA games at Embark Studios. From Blender to Unreal Engine!\n\nAlso... geometry nodes anyone?\n\n* Embark Studios: https://embark.games\n* Embark Studios Twitter: https://twitter.com/EmbarkStudios\n* Daniel Bystedt: https://twitter.com/3DBystedt\n\n==\n\nBlenderToday Links:\n* Chat: https://blender.chat/channel/today\n* Community: http://blender.today\n* Twitter: https://twitter.com/BlenderToday\n* YouTube - https://www.youtube.com/BlenderCommunity\n\n--\n\nPablo Vazquez Links: \n* Instagram - https://instagram.com/pablovazquez.art\n* Twitter - https://twitter.com/pablovazquez_\n* YouTube - https://www.youtube.com/PabloVazquez\n* ArtStation - https://artstation.com/pablovazquez\n\nSupport core Blender development - https://fund.blender.org\n\n#BlenderToday #b3d➡️","thumbnails":{"default":{"url":"https://i.ytimg.com/vi/oqjKMd9CYI4/default.jpg","width":120,"height":90},"medium":{"url":"https://i.ytimg.com/vi/oqjKMd9CYI4/mqdefault.jpg","width":320,"height":180},"high":{"url":"https://i.ytimg.com/vi/oqjKMd9CYI4/hqdefault.jpg","width":480,"height":360},"standard":{"url":"https://i.ytimg.com/vi/oqjKMd9CYI4/sddefault.jpg","width":640,"height":480},"maxres":{"url":"https://i.ytimg.com/vi/oqjKMd9CYI4/maxresdefault.jpg","width":1280,"height":720}},"channelTitle":"Blender","playlistId":"PLa1F2ddGya_87HJ72v_IgKUTNLIXSMfvB","position":9,"resourceId":{"kind":"youtube#video","videoId":"oqjKMd9CYI4"},"videoOwnerChannelTitle":"Blender","videoOwnerChannelId":"UCSMOQeBJ2RAnuFungnQOxLg"},"contentDetails":{"videoId":"oqjKMd9CYI4","videoPublishedAt":"2020-11-30T17:14:43Z"},"status":{"privacyStatus":"public"}},{"kind":"youtube#playlistItem","etag":"MzyF4XdzT85bzNBH5y7Gh2rw1KQ","id":"UExhMUYyZGRHeWFfODdISjcydl9JZ0tVVE5MSVhTTWZ2Qi5CNEFEOUNDRUMzMjVGMjc2","snippet":{"publishedAt":"2020-11-25T14:56:46Z","channelId":"UCSMOQeBJ2RAnuFungnQOxLg","title":"BLENDER 2.91 RELEASE #128 | Blender.Today LIVE","description":"It's happening! Let's watch 2.91 go live, while live!\n\n==\n\nBlenderToday Links:\n* Chat: https://blender.chat/channel/today\n* Community: http://blender.today\n* Twitter: https://twitter.com/BlenderToday\n* YouTube - https://www.youtube.com/BlenderCommunity\n\n--\n\nPablo Vazquez Links: \n* Instagram - https://instagram.com/pablovazquez.art\n* Twitter - https://twitter.com/pablovazquez_\n* YouTube - https://www.youtube.com/PabloVazquez\n* ArtStation - https://artstation.com/pablovazquez\n\nSupport core Blender development - https://fund.blender.org\n\n#BlenderToday #b3d➡️","thumbnails":{"default":{"url":"https://i.ytimg.com/vi/ZH73tPk81sY/default.jpg","width":120,"height":90},"medium":{"url":"https://i.ytimg.com/vi/ZH73tPk81sY/mqdefault.jpg","width":320,"height":180},"high":{"url":"https://i.ytimg.com/vi/ZH73tPk81sY/hqdefault.jpg","width":480,"height":360},"standard":{"url":"https://i.ytimg.com/vi/ZH73tPk81sY/sddefault.jpg","width":640,"height":480},"maxres":{"url":"https://i.ytimg.com/vi/ZH73tPk81sY/maxresdefault.jpg","width":1280,"height":720}},"channelTitle":"Blender","playlistId":"PLa1F2ddGya_87HJ72v_IgKUTNLIXSMfvB","position":10,"resourceId":{"kind":"youtube#video","videoId":"ZH73tPk81sY"},"videoOwnerChannelTitle":"Blender","videoOwnerChannelId":"UCSMOQeBJ2RAnuFungnQOxLg"},"contentDetails":{"videoId":"ZH73tPk81sY","videoPublishedAt":"2020-11-25T17:44:48Z"},"status":{"privacyStatus":"public"}},{"kind":"youtube#playlistItem","etag":"5SBzwmEQTtzRoBYPuxshFLx90a0","id":"UExhMUYyZGRHeWFfODdISjcydl9JZ0tVVE5MSVhTTWZ2Qi45NDIzMEVBNjk5NTFGRDZC","snippet":{"publishedAt":"2020-11-16T14:28:59Z","channelId":"UCSMOQeBJ2RAnuFungnQOxLg","title":"GREASE PENCIL CURVE EDIT! #127 | Blender.Today LIVE","description":"Edit your Grease Pencil curves in a much simpler way! \nTHREAD: https://blender.community/c/today/\n\n==\n\nBlenderToday Links:\n* Chat: https://blender.chat/channel/today\n* Community: http://blender.today\n* Twitter: https://twitter.com/BlenderToday\n* YouTube - https://www.youtube.com/BlenderCommunity\n\n--\n\nPablo Vazquez Links: \n* Instagram - https://instagram.com/pablovazquez.art\n* Twitter - https://twitter.com/pablovazquez_\n* YouTube - https://www.youtube.com/PabloVazquez\n* ArtStation - https://artstation.com/pablovazquez\n\nSupport core Blender development - https://fund.blender.org\n\n#BlenderToday #b3d➡️","thumbnails":{"default":{"url":"https://i.ytimg.com/vi/LVDFyT0wYaw/default.jpg","width":120,"height":90},"medium":{"url":"https://i.ytimg.com/vi/LVDFyT0wYaw/mqdefault.jpg","width":320,"height":180},"high":{"url":"https://i.ytimg.com/vi/LVDFyT0wYaw/hqdefault.jpg","width":480,"height":360}},"channelTitle":"Blender","playlistId":"PLa1F2ddGya_87HJ72v_IgKUTNLIXSMfvB","position":11,"resourceId":{"kind":"youtube#video","videoId":"LVDFyT0wYaw"},"videoOwnerChannelTitle":"Blender","videoOwnerChannelId":"UCSMOQeBJ2RAnuFungnQOxLg"},"contentDetails":{"videoId":"LVDFyT0wYaw","videoPublishedAt":"2020-11-16T17:33:55Z"},"status":{"privacyStatus":"public"}},{"kind":"youtube#playlistItem","etag":"d1jsDRGW7XUSMTi9k161G_xS5h8","id":"UExhMUYyZGRHeWFfODdISjcydl9JZ0tVVE5MSVhTTWZ2Qi5CODNEOTFERDNCQjU2ODhE","snippet":{"publishedAt":"2020-11-09T15:34:20Z","channelId":"UCSMOQeBJ2RAnuFungnQOxLg","title":"GEOMETRY NODES ft Dalai! #126 | Blender.Today LIVE","description":"Geometry Nodes? What's all that about? \nTHREAD: https://blender.community/c/today/\n\n==\n\nBlenderToday Links:\n* Chat: https://blender.chat/channel/today\n* Community: http://blender.today\n* Twitter: https://twitter.com/BlenderToday\n* YouTube - https://www.youtube.com/BlenderCommunity\n\n--\n\nPablo Vazquez Links: \n* Instagram - https://instagram.com/pablovazquez.art\n* Twitter - https://twitter.com/pablovazquez_\n* YouTube - https://www.youtube.com/PabloVazquez\n* ArtStation - https://artstation.com/pablovazquez\n\nSupport core Blender development - https://fund.blender.org\n\n#BlenderToday #b3d➡️","thumbnails":{"default":{"url":"https://i.ytimg.com/vi/GcwgvZOBzAE/default.jpg","width":120,"height":90},"medium":{"url":"https://i.ytimg.com/vi/GcwgvZOBzAE/mqdefault.jpg","width":320,"height":180},"high":{"url":"https://i.ytimg.com/vi/GcwgvZOBzAE/hqdefault.jpg","width":480,"height":360},"standard":{"url":"https://i.ytimg.com/vi/GcwgvZOBzAE/sddefault.jpg","width":640,"height":480},"maxres":{"url":"https://i.ytimg.com/vi/GcwgvZOBzAE/maxresdefault.jpg","width":1280,"height":720}},"channelTitle":"Blender","playlistId":"PLa1F2ddGya_87HJ72v_IgKUTNLIXSMfvB","position":12,"resourceId":{"kind":"youtube#video","videoId":"GcwgvZOBzAE"},"videoOwnerChannelTitle":"Blender","videoOwnerChannelId":"UCSMOQeBJ2RAnuFungnQOxLg"},"contentDetails":{"videoId":"GcwgvZOBzAE","videoPublishedAt":"2020-11-09T17:32:08Z"},"status":{"privacyStatus":"public"}},{"kind":"youtube#playlistItem","etag":"TlKdev-UjVrJEwmMOEABZDwwh2s","id":"UExhMUYyZGRHeWFfODdISjcydl9JZ0tVVE5MSVhTTWZ2Qi40QTY5NjQzQkQzMjgwNjhD","snippet":{"publishedAt":"2020-11-02T15:50:25Z","channelId":"UCSMOQeBJ2RAnuFungnQOxLg","title":"BCON blues + Q&A #125 | Blender.Today LIVE","description":"Monday's after a Blender Conference are always tough, but hey there's a lot of new stuff to share!\nTHREAD: https://blender.community/c/today/\n\n==\n\nBlenderToday Links:\n* Chat: https://blender.chat/channel/today\n* Community: http://blender.today\n* Twitter: https://twitter.com/BlenderToday\n* YouTube - https://www.youtube.com/BlenderCommunity\n\n--\n\nPablo Vazquez Links: \n* Instagram - https://instagram.com/pablovazquez.art\n* Twitter - https://twitter.com/pablovazquez_\n* YouTube - https://www.youtube.com/PabloVazquez\n* ArtStation - https://artstation.com/pablovazquez\n\nSupport core Blender development - https://fund.blender.org\n\n#BlenderToday #b3d➡️","thumbnails":{"default":{"url":"https://i.ytimg.com/vi/YuqWB8PORDM/default.jpg","width":120,"height":90},"medium":{"url":"https://i.ytimg.com/vi/YuqWB8PORDM/mqdefault.jpg","width":320,"height":180},"high":{"url":"https://i.ytimg.com/vi/YuqWB8PORDM/hqdefault.jpg","width":480,"height":360},"standard":{"url":"https://i.ytimg.com/vi/YuqWB8PORDM/sddefault.jpg","width":640,"height":480},"maxres":{"url":"https://i.ytimg.com/vi/YuqWB8PORDM/maxresdefault.jpg","width":1280,"height":720}},"channelTitle":"Blender","playlistId":"PLa1F2ddGya_87HJ72v_IgKUTNLIXSMfvB","position":13,"resourceId":{"kind":"youtube#video","videoId":"YuqWB8PORDM"},"videoOwnerChannelTitle":"Blender","videoOwnerChannelId":"UCSMOQeBJ2RAnuFungnQOxLg"},"contentDetails":{"videoId":"YuqWB8PORDM","videoPublishedAt":"2020-11-02T17:34:24Z"},"status":{"privacyStatus":"public"}},{"kind":"youtube#playlistItem","etag":"ki_9S-bjGgULyyOdmBZ7YEwBYxI","id":"UExhMUYyZGRHeWFfODdISjcydl9JZ0tVVE5MSVhTTWZ2Qi5DNTU3ODQ4ODAzMjFERTI1","snippet":{"publishedAt":"2020-10-26T14:59:23Z","channelId":"UCSMOQeBJ2RAnuFungnQOxLg","title":"2.92 ALPHA + Q&A #124 | Blender.Today LIVE","description":"Answering the Blender community's top questions of the week. THREAD: https://blender.community/c/today/\n\n==\n\nBlenderToday Links:\n* Chat: https://blender.chat/channel/today\n* Community: http://blender.today\n* Twitter: https://twitter.com/BlenderToday\n* YouTube - https://www.youtube.com/BlenderCommunity\n\n--\n\nPablo Vazquez Links: \n* Instagram - https://instagram.com/pablovazquez.art\n* Twitter - https://twitter.com/pablovazquez_\n* YouTube - https://www.youtube.com/PabloVazquez\n* ArtStation - https://artstation.com/pablovazquez\n\nSupport core Blender development - https://fund.blender.org\n\n#BlenderToday #b3d➡️","thumbnails":{"default":{"url":"https://i.ytimg.com/vi/N-IyNNfvlcI/default.jpg","width":120,"height":90},"medium":{"url":"https://i.ytimg.com/vi/N-IyNNfvlcI/mqdefault.jpg","width":320,"height":180},"high":{"url":"https://i.ytimg.com/vi/N-IyNNfvlcI/hqdefault.jpg","width":480,"height":360},"standard":{"url":"https://i.ytimg.com/vi/N-IyNNfvlcI/sddefault.jpg","width":640,"height":480},"maxres":{"url":"https://i.ytimg.com/vi/N-IyNNfvlcI/maxresdefault.jpg","width":1280,"height":720}},"channelTitle":"Blender","playlistId":"PLa1F2ddGya_87HJ72v_IgKUTNLIXSMfvB","position":14,"resourceId":{"kind":"youtube#video","videoId":"N-IyNNfvlcI"},"videoOwnerChannelTitle":"Blender","videoOwnerChannelId":"UCSMOQeBJ2RAnuFungnQOxLg"},"contentDetails":{"videoId":"N-IyNNfvlcI","videoPublishedAt":"2020-10-26T17:32:32Z"},"status":{"privacyStatus":"public"}},{"kind":"youtube#playlistItem","etag":"q4c2R5oLrMQJnpg3cSJcg_DBvjU","id":"UExhMUYyZGRHeWFfODdISjcydl9JZ0tVVE5MSVhTTWZ2Qi4wMTIyMTBBMTA3RDUxNjlD","snippet":{"publishedAt":"2020-10-19T13:28:26Z","channelId":"UCSMOQeBJ2RAnuFungnQOxLg","title":"ANIMATION + Q&A #123 | Blender.Today LIVE","description":"Answering the Blender community's top questions of the week. THREAD: https://blender.community/c/today/\n\n==\n\nBlenderToday Links:\n* Chat: https://blender.chat/channel/today\n* Community: http://blender.today\n* Twitter: https://twitter.com/BlenderToday\n* YouTube - https://www.youtube.com/BlenderCommunity\n\n--\n\nPablo Vazquez Links: \n* Instagram - https://instagram.com/pablovazquez.art\n* Twitter - https://twitter.com/pablovazquez_\n* YouTube - https://www.youtube.com/PabloVazquez\n* ArtStation - https://artstation.com/pablovazquez\n\nSupport core Blender development - https://fund.blender.org\n\n#BlenderToday #b3d➡️","thumbnails":{"default":{"url":"https://i.ytimg.com/vi/IH2pGcHe2Yo/default.jpg","width":120,"height":90},"medium":{"url":"https://i.ytimg.com/vi/IH2pGcHe2Yo/mqdefault.jpg","width":320,"height":180},"high":{"url":"https://i.ytimg.com/vi/IH2pGcHe2Yo/hqdefault.jpg","width":480,"height":360},"standard":{"url":"https://i.ytimg.com/vi/IH2pGcHe2Yo/sddefault.jpg","width":640,"height":480},"maxres":{"url":"https://i.ytimg.com/vi/IH2pGcHe2Yo/maxresdefault.jpg","width":1280,"height":720}},"channelTitle":"Blender","playlistId":"PLa1F2ddGya_87HJ72v_IgKUTNLIXSMfvB","position":15,"resourceId":{"kind":"youtube#video","videoId":"IH2pGcHe2Yo"},"videoOwnerChannelTitle":"Blender","videoOwnerChannelId":"UCSMOQeBJ2RAnuFungnQOxLg"},"contentDetails":{"videoId":"IH2pGcHe2Yo","videoPublishedAt":"2020-10-19T16:29:14Z"},"status":{"privacyStatus":"public"}},{"kind":"youtube#playlistItem","etag":"rkzemCQO8-o41vHT0bpi7k_3RYg","id":"UExhMUYyZGRHeWFfODdISjcydl9JZ0tVVE5MSVhTTWZ2Qi40Q0JERDMxNzcwNTk1M0Y0","snippet":{"publishedAt":"2020-10-12T14:27:08Z","channelId":"UCSMOQeBJ2RAnuFungnQOxLg","title":"VOLUMES! Q&A #122 | Blender.Today LIVE","description":"Answering the Blender community's top questions of the week. THREAD: https://blender.community/c/today/\n\n==\n\nBlenderToday Links:\n* Chat: https://blender.chat/channel/today\n* Community: http://blender.today\n* Twitter: https://twitter.com/BlenderToday\n* YouTube - https://www.youtube.com/BlenderCommunity\n\n--\n\nPablo Vazquez Links: \n* Instagram - https://instagram.com/pablovazquez.art\n* Twitter - https://twitter.com/pablovazquez_\n* YouTube - https://www.youtube.com/PabloVazquez\n* ArtStation - https://artstation.com/pablovazquez\n\nSupport core Blender development - https://fund.blender.org\n\n#BlenderToday #b3d➡️","thumbnails":{"default":{"url":"https://i.ytimg.com/vi/lbbmVreDl_o/default.jpg","width":120,"height":90},"medium":{"url":"https://i.ytimg.com/vi/lbbmVreDl_o/mqdefault.jpg","width":320,"height":180},"high":{"url":"https://i.ytimg.com/vi/lbbmVreDl_o/hqdefault.jpg","width":480,"height":360},"standard":{"url":"https://i.ytimg.com/vi/lbbmVreDl_o/sddefault.jpg","width":640,"height":480},"maxres":{"url":"https://i.ytimg.com/vi/lbbmVreDl_o/maxresdefault.jpg","width":1280,"height":720}},"channelTitle":"Blender","playlistId":"PLa1F2ddGya_87HJ72v_IgKUTNLIXSMfvB","position":16,"resourceId":{"kind":"youtube#video","videoId":"lbbmVreDl_o"},"videoOwnerChannelTitle":"Blender","videoOwnerChannelId":"UCSMOQeBJ2RAnuFungnQOxLg"},"contentDetails":{"videoId":"lbbmVreDl_o","videoPublishedAt":"2020-10-12T17:34:07Z"},"status":{"privacyStatus":"public"}},{"kind":"youtube#playlistItem","etag":"OJ-Crdas9CuLF87Drej61cngJ68","id":"UExhMUYyZGRHeWFfODdISjcydl9JZ0tVVE5MSVhTTWZ2Qi40NTBGRDE5MDg2Q0NEODI4","snippet":{"publishedAt":"2020-09-28T14:54:40Z","channelId":"UCSMOQeBJ2RAnuFungnQOxLg","title":"EEVEE GGX Multi-Scatter! Q&A #121 | Blender.Today LIVE","description":"Answering the Blender community's top questions of the week. THREAD: https://blender.community/c/today/\n\n==\n\nBlenderToday Links:\n* Chat: https://blender.chat/channel/today\n* Community: http://blender.today\n* Twitter: https://twitter.com/BlenderToday\n* YouTube - https://www.youtube.com/BlenderCommunity\n\n--\n\nPablo Vazquez Links: \n* Instagram - https://instagram.com/pablovazquez.art\n* Twitter - https://twitter.com/pablovazquez_\n* YouTube - https://www.youtube.com/PabloVazquez\n* ArtStation - https://artstation.com/pablovazquez\n\nSupport core Blender development - https://fund.blender.org\n\n#BlenderToday #b3d➡️","thumbnails":{"default":{"url":"https://i.ytimg.com/vi/Mkj338ytNPQ/default.jpg","width":120,"height":90},"medium":{"url":"https://i.ytimg.com/vi/Mkj338ytNPQ/mqdefault.jpg","width":320,"height":180},"high":{"url":"https://i.ytimg.com/vi/Mkj338ytNPQ/hqdefault.jpg","width":480,"height":360}},"channelTitle":"Blender","playlistId":"PLa1F2ddGya_87HJ72v_IgKUTNLIXSMfvB","position":17,"resourceId":{"kind":"youtube#video","videoId":"Mkj338ytNPQ"},"videoOwnerChannelTitle":"Blender","videoOwnerChannelId":"UCSMOQeBJ2RAnuFungnQOxLg"},"contentDetails":{"videoId":"Mkj338ytNPQ","videoPublishedAt":"2020-09-28T16:24:23Z"},"status":{"privacyStatus":"public"}},{"kind":"youtube#playlistItem","etag":"kwiP6h3zynZVrmy-Mb3b0gtux4w","id":"UExhMUYyZGRHeWFfODdISjcydl9JZ0tVVE5MSVhTTWZ2Qi42NjBGMkRFNDcwMjM2NzYx","snippet":{"publishedAt":"2020-09-21T12:24:44Z","channelId":"UCSMOQeBJ2RAnuFungnQOxLg","title":"MONDAY! Q&A #120 | Blender.Today LIVE","description":"Mondays are great again! Answering the Blender community's top questions of the week. THREAD: https://blender.community/c/today/Xkgbbc/\n\n==\n\nBlenderToday Links:\n* Chat: https://blender.chat/channel/today\n* Community: http://blender.today\n* Twitter: https://twitter.com/BlenderToday\n* YouTube - https://www.youtube.com/BlenderCommunity\n\n--\n\nPablo Vazquez Links: \n* Instagram - https://instagram.com/pablovazquez.art\n* Twitter - https://twitter.com/pablovazquez_\n* YouTube - https://www.youtube.com/PabloVazquez\n* ArtStation - https://artstation.com/pablovazquez\n\nSupport core Blender development - https://fund.blender.org\n\n#BlenderToday #b3d➡️","thumbnails":{"default":{"url":"https://i.ytimg.com/vi/jCiqUQueTH0/default.jpg","width":120,"height":90},"medium":{"url":"https://i.ytimg.com/vi/jCiqUQueTH0/mqdefault.jpg","width":320,"height":180},"high":{"url":"https://i.ytimg.com/vi/jCiqUQueTH0/hqdefault.jpg","width":480,"height":360},"standard":{"url":"https://i.ytimg.com/vi/jCiqUQueTH0/sddefault.jpg","width":640,"height":480},"maxres":{"url":"https://i.ytimg.com/vi/jCiqUQueTH0/maxresdefault.jpg","width":1280,"height":720}},"channelTitle":"Blender","playlistId":"PLa1F2ddGya_87HJ72v_IgKUTNLIXSMfvB","position":18,"resourceId":{"kind":"youtube#video","videoId":"jCiqUQueTH0"},"videoOwnerChannelTitle":"Blender","videoOwnerChannelId":"UCSMOQeBJ2RAnuFungnQOxLg"},"contentDetails":{"videoId":"jCiqUQueTH0","videoPublishedAt":"2020-09-21T16:21:11Z"},"status":{"privacyStatus":"public"}},{"kind":"youtube#playlistItem","etag":"l2zez_M7CQp_Ug0zi4-_Vmw-PEs","id":"UExhMUYyZGRHeWFfODdISjcydl9JZ0tVVE5MSVhTTWZ2Qi5BNTRGQTE1QjY2NUE5NTAz","snippet":{"publishedAt":"2020-09-14T14:34:36Z","channelId":"UCSMOQeBJ2RAnuFungnQOxLg","title":"MONDAY! Q&A #119 | Blender.Today LIVE","description":"Mondays are great again! Answering the Blender community's top questions of the week.\n\n==\n\nBlenderToday Links:\n* Chat: https://blender.chat/channel/today\n* Community: http://blender.today\n* Twitter: https://twitter.com/BlenderToday\n* YouTube - https://www.youtube.com/BlenderCommunity\n\n--\n\nPablo Vazquez Links: \n* Instagram - https://instagram.com/pablovazquez.art\n* Twitter - https://twitter.com/pablovazquez_\n* YouTube - https://www.youtube.com/PabloVazquez\n* ArtStation - https://artstation.com/pablovazquez\n\nSupport core Blender development - https://fund.blender.org\n\n#BlenderToday #b3d➡️","thumbnails":{"default":{"url":"https://i.ytimg.com/vi/n4sGp5QCl18/default.jpg","width":120,"height":90},"medium":{"url":"https://i.ytimg.com/vi/n4sGp5QCl18/mqdefault.jpg","width":320,"height":180},"high":{"url":"https://i.ytimg.com/vi/n4sGp5QCl18/hqdefault.jpg","width":480,"height":360},"standard":{"url":"https://i.ytimg.com/vi/n4sGp5QCl18/sddefault.jpg","width":640,"height":480}},"channelTitle":"Blender","playlistId":"PLa1F2ddGya_87HJ72v_IgKUTNLIXSMfvB","position":19,"resourceId":{"kind":"youtube#video","videoId":"n4sGp5QCl18"},"videoOwnerChannelTitle":"Blender","videoOwnerChannelId":"UCSMOQeBJ2RAnuFungnQOxLg"},"contentDetails":{"videoId":"n4sGp5QCl18","videoPublishedAt":"2020-09-14T16:18:28Z"},"status":{"privacyStatus":"public"}},{"kind":"youtube#playlistItem","etag":"QxhEe2mW9YuBfORW6ntJO0K701Q","id":"UExhMUYyZGRHeWFfODdISjcydl9JZ0tVVE5MSVhTTWZ2Qi5FOTE3RTBFMjNFMDNEM0Yz","snippet":{"publishedAt":"2020-09-04T14:49:22Z","channelId":"UCSMOQeBJ2RAnuFungnQOxLg","title":"Q&A #118 | Blender.Today LIVE","description":"Answering the community's top questions of the week!\n\n==\n\nBlenderToday Links:\n* Chat: https://blender.chat/channel/today\n* Community: http://blender.today\n* Twitter: https://twitter.com/BlenderToday\n* YouTube - https://www.youtube.com/BlenderCommunity\n\n--\n\nPablo Vazquez Links: \n* Instagram - https://instagram.com/pablovazquez.art\n* Twitter - https://twitter.com/pablovazquez_\n* YouTube - https://www.youtube.com/PabloVazquez\n* ArtStation - https://artstation.com/pablovazquez\n\nSupport core Blender development - https://fund.blender.org\n\n#BlenderToday #b3d➡️","thumbnails":{"default":{"url":"https://i.ytimg.com/vi/hS7iV3NfddI/default.jpg","width":120,"height":90},"medium":{"url":"https://i.ytimg.com/vi/hS7iV3NfddI/mqdefault.jpg","width":320,"height":180},"high":{"url":"https://i.ytimg.com/vi/hS7iV3NfddI/hqdefault.jpg","width":480,"height":360}},"channelTitle":"Blender","playlistId":"PLa1F2ddGya_87HJ72v_IgKUTNLIXSMfvB","position":20,"resourceId":{"kind":"youtube#video","videoId":"hS7iV3NfddI"},"videoOwnerChannelTitle":"Blender","videoOwnerChannelId":"UCSMOQeBJ2RAnuFungnQOxLg"},"contentDetails":{"videoId":"hS7iV3NfddI","videoPublishedAt":"2020-09-04T16:34:50Z"},"status":{"privacyStatus":"public"}},{"kind":"youtube#playlistItem","etag":"ToD1xQZ1R1jUMiFAz-pbRjOpi5A","id":"UExhMUYyZGRHeWFfODdISjcydl9JZ0tVVE5MSVhTTWZ2Qi5FMjFERkYxMjI2NjkyMjg5","snippet":{"publishedAt":"2020-08-28T14:28:19Z","channelId":"UCSMOQeBJ2RAnuFungnQOxLg","title":"WHERE'S 2.90? Q&A #117 | Blender.Today LIVE","description":"Answering the community's top questions of the week!\n\n==\n\nBlenderToday Links:\n* Chat: https://blender.chat/channel/today\n* Community: http://blender.today\n* Twitter: https://twitter.com/BlenderToday\n* YouTube - https://www.youtube.com/BlenderCommunity\n\n--\n\nPablo Vazquez Links: \n* Instagram - https://instagram.com/pablovazquez.art\n* Twitter - https://twitter.com/pablovazquez_\n* YouTube - https://www.youtube.com/PabloVazquez\n* ArtStation - https://artstation.com/pablovazquez\n\nSupport core Blender development - https://fund.blender.org\n\n#BlenderToday #b3d➡️","thumbnails":{"default":{"url":"https://i.ytimg.com/vi/MW-wn9htHFM/default.jpg","width":120,"height":90},"medium":{"url":"https://i.ytimg.com/vi/MW-wn9htHFM/mqdefault.jpg","width":320,"height":180},"high":{"url":"https://i.ytimg.com/vi/MW-wn9htHFM/hqdefault.jpg","width":480,"height":360},"standard":{"url":"https://i.ytimg.com/vi/MW-wn9htHFM/sddefault.jpg","width":640,"height":480}},"channelTitle":"Blender","playlistId":"PLa1F2ddGya_87HJ72v_IgKUTNLIXSMfvB","position":21,"resourceId":{"kind":"youtube#video","videoId":"MW-wn9htHFM"},"videoOwnerChannelTitle":"Blender","videoOwnerChannelId":"UCSMOQeBJ2RAnuFungnQOxLg"},"contentDetails":{"videoId":"MW-wn9htHFM","videoPublishedAt":"2020-08-28T16:13:44Z"},"status":{"privacyStatus":"public"}},{"kind":"youtube#playlistItem","etag":"at5N6OCUWM5MkY4SnXb3ObUyMoo","id":"UExhMUYyZGRHeWFfODdISjcydl9JZ0tVVE5MSVhTTWZ2Qi4zMkY2MjA3RDJERTkxNjkz","snippet":{"publishedAt":"2020-08-21T10:47:58Z","channelId":"UCSMOQeBJ2RAnuFungnQOxLg","title":"NEW SPONSOR! + Q&A | Blender.Today LIVE #116","description":"Answering the Blender community's top questions of the week!\n➡️ Q&A THREAD: https://blender.community/c/today/hbgbbc/\n\n==\n\nBlenderToday Links:\n* Chat: https://blender.chat/channel/today\n* Community: http://blender.today\n* Twitter: https://twitter.com/BlenderToday\n* YouTube - https://www.youtube.com/BlenderCommunity\n\n--\n\nPablo Vazquez Links: \n* Instagram - https://instagram.com/pablovazquez.art\n* Twitter - https://twitter.com/pablovazquez_\n* YouTube - https://www.youtube.com/PabloVazquez\n* ArtStation - https://artstation.com/pablovazquez\n\nSupport core Blender development - https://fund.blender.org\n\n#BlenderToday #b3d➡️","thumbnails":{"default":{"url":"https://i.ytimg.com/vi/9V8csSkODmQ/default.jpg","width":120,"height":90},"medium":{"url":"https://i.ytimg.com/vi/9V8csSkODmQ/mqdefault.jpg","width":320,"height":180},"high":{"url":"https://i.ytimg.com/vi/9V8csSkODmQ/hqdefault.jpg","width":480,"height":360},"standard":{"url":"https://i.ytimg.com/vi/9V8csSkODmQ/sddefault.jpg","width":640,"height":480}},"channelTitle":"Blender","playlistId":"PLa1F2ddGya_87HJ72v_IgKUTNLIXSMfvB","position":22,"resourceId":{"kind":"youtube#video","videoId":"9V8csSkODmQ"},"videoOwnerChannelTitle":"Blender","videoOwnerChannelId":"UCSMOQeBJ2RAnuFungnQOxLg"},"contentDetails":{"videoId":"9V8csSkODmQ","videoPublishedAt":"2020-08-21T16:31:58Z"},"status":{"privacyStatus":"public"}},{"kind":"youtube#playlistItem","etag":"8N8woN9z1h2coS7YIaJW1-7__jU","id":"UExhMUYyZGRHeWFfODdISjcydl9JZ0tVVE5MSVhTTWZ2Qi5DNUEzOUFFNkIyOUUzOTRC","snippet":{"publishedAt":"2020-08-07T10:43:41Z","channelId":"UCSMOQeBJ2RAnuFungnQOxLg","title":"Q&A #115 | Blender.Today LIVE","description":"Ask away on BlenderToday!\nQ&A THREAD ➡️ https://blender.community/c/today/dXfbbc/\n\nAnswering the community's top questions of the week!\n\n==\n\nBlenderToday Links:\n* Chat: https://blender.chat/channel/today\n* Community: http://blender.today\n* Twitter: https://twitter.com/BlenderToday\n* YouTube - https://www.youtube.com/BlenderCommunity\n\n--\n\nPablo Vazquez Links: \n* Instagram - https://instagram.com/pablovazquez.art\n* Twitter - https://twitter.com/pablovazquez_\n* YouTube - https://www.youtube.com/PabloVazquez\n* ArtStation - https://artstation.com/pablovazquez\n\nSupport core Blender development - https://fund.blender.org\n\n#Q&A #BlenderToday #b3d➡️","thumbnails":{"default":{"url":"https://i.ytimg.com/vi/yCU-T7pbYgk/default.jpg","width":120,"height":90},"medium":{"url":"https://i.ytimg.com/vi/yCU-T7pbYgk/mqdefault.jpg","width":320,"height":180},"high":{"url":"https://i.ytimg.com/vi/yCU-T7pbYgk/hqdefault.jpg","width":480,"height":360},"standard":{"url":"https://i.ytimg.com/vi/yCU-T7pbYgk/sddefault.jpg","width":640,"height":480}},"channelTitle":"Blender","playlistId":"PLa1F2ddGya_87HJ72v_IgKUTNLIXSMfvB","position":23,"resourceId":{"kind":"youtube#video","videoId":"yCU-T7pbYgk"},"videoOwnerChannelTitle":"Blender","videoOwnerChannelId":"UCSMOQeBJ2RAnuFungnQOxLg"},"contentDetails":{"videoId":"yCU-T7pbYgk","videoPublishedAt":"2020-08-07T16:17:12Z"},"status":{"privacyStatus":"public"}},{"kind":"youtube#playlistItem","etag":"WpQT3qAWyfNDxx4-Yo2F7375UEo","id":"UExhMUYyZGRHeWFfODdISjcydl9JZ0tVVE5MSVhTTWZ2Qi4xRjE1NzQ4MjRCMUNFRDdB","snippet":{"publishedAt":"2020-07-30T17:10:42Z","channelId":"UCSMOQeBJ2RAnuFungnQOxLg","title":"DEV FUND - Q&A #114 | Blender.Today LIVE","description":"Ask away on BlenderToday!\nQ&A THREAD ➡️ https://blender.community/c/today/HSfbbc/\n\nAnswering the community's top questions of the week!\n\n==\n\nBlenderToday Links:\n* Chat: https://blender.chat/channel/today\n* Community: http://blender.today\n* Twitter: https://twitter.com/BlenderToday\n* YouTube - https://www.youtube.com/BlenderCommunity\n\n--\n\nPablo Vazquez Links: \n* Instagram - https://instagram.com/pablovazquez.art\n* Twitter - https://twitter.com/pablovazquez_\n* YouTube - https://www.youtube.com/PabloVazquez\n* ArtStation - https://artstation.com/pablovazquez\n\nSupport core Blender development - https://fund.blender.org\n\n#Q&A #BlenderToday #b3d➡️","thumbnails":{"default":{"url":"https://i.ytimg.com/vi/SlB2S54pa9I/default.jpg","width":120,"height":90},"medium":{"url":"https://i.ytimg.com/vi/SlB2S54pa9I/mqdefault.jpg","width":320,"height":180},"high":{"url":"https://i.ytimg.com/vi/SlB2S54pa9I/hqdefault.jpg","width":480,"height":360},"standard":{"url":"https://i.ytimg.com/vi/SlB2S54pa9I/sddefault.jpg","width":640,"height":480},"maxres":{"url":"https://i.ytimg.com/vi/SlB2S54pa9I/maxresdefault.jpg","width":1280,"height":720}},"channelTitle":"Blender","playlistId":"PLa1F2ddGya_87HJ72v_IgKUTNLIXSMfvB","position":24,"resourceId":{"kind":"youtube#video","videoId":"SlB2S54pa9I"},"videoOwnerChannelTitle":"Blender","videoOwnerChannelId":"UCSMOQeBJ2RAnuFungnQOxLg"},"contentDetails":{"videoId":"SlB2S54pa9I","videoPublishedAt":"2020-07-31T16:22:14Z"},"status":{"privacyStatus":"public"}},{"kind":"youtube#playlistItem","etag":"0u3_NZt06qP2M8q4s9P-iRK1sj8","id":"UExhMUYyZGRHeWFfODdISjcydl9JZ0tVVE5MSVhTTWZ2Qi5EQTdFNDU3M0Y3MTM1QjlG","snippet":{"publishedAt":"2020-07-23T14:28:06Z","channelId":"UCSMOQeBJ2RAnuFungnQOxLg","title":"Blender 2.91 ALPHA! Q&A #113 | Blender.Today LIVE","description":"Ask away on BlenderToday!\nQ&A THREAD ➡️ https://blender.community/c/today/8Gfbbc/\n\nAnswering the community's top 20 questions of the week!\n\n==\n\nBlenderToday Links:\n* Chat: https://blender.chat/channel/today\n* Community: http://blender.today\n* Twitter: https://twitter.com/BlenderToday\n* YouTube - https://www.youtube.com/BlenderCommunity\n\n--\n\nPablo Vazquez Links: \n* Instagram - https://instagram.com/pablovazquez.art\n* Twitter - https://twitter.com/pablovazquez_\n* YouTube - https://www.youtube.com/PabloVazquez\n* ArtStation - https://artstation.com/pablovazquez\n\nSupport core Blender development - https://fund.blender.org\n\n#Q&A #BlenderToday #b3d➡️","thumbnails":{"default":{"url":"https://i.ytimg.com/vi/kxDySLYU4XI/default.jpg","width":120,"height":90},"medium":{"url":"https://i.ytimg.com/vi/kxDySLYU4XI/mqdefault.jpg","width":320,"height":180},"high":{"url":"https://i.ytimg.com/vi/kxDySLYU4XI/hqdefault.jpg","width":480,"height":360},"standard":{"url":"https://i.ytimg.com/vi/kxDySLYU4XI/sddefault.jpg","width":640,"height":480}},"channelTitle":"Blender","playlistId":"PLa1F2ddGya_87HJ72v_IgKUTNLIXSMfvB","position":25,"resourceId":{"kind":"youtube#video","videoId":"kxDySLYU4XI"},"videoOwnerChannelTitle":"Blender","videoOwnerChannelId":"UCSMOQeBJ2RAnuFungnQOxLg"},"contentDetails":{"videoId":"kxDySLYU4XI","videoPublishedAt":"2020-07-24T16:19:49Z"},"status":{"privacyStatus":"public"}},{"kind":"youtube#playlistItem","etag":"sJY4-Rnqmw1zoBWOHy2siB1BXtc","id":"UExhMUYyZGRHeWFfODdISjcydl9JZ0tVVE5MSVhTTWZ2Qi4wNjIzRDA1OTQ2M0UyODEw","snippet":{"publishedAt":"2020-07-17T09:06:16Z","channelId":"UCSMOQeBJ2RAnuFungnQOxLg","title":"Ask Blender Anything! Q&A #112 | Blender.Today Live","description":"Ask away on BlenderToday!\nQ&A THREAD ➡️ https://blender.community/c/today/08fbbc/\n\nAnswering the community's top 20 questions of the week!\n\n==\n\nBlenderToday Links:\n* Chat: https://blender.chat/channel/today\n* Community: http://blender.today\n* Twitter: https://twitter.com/BlenderToday\n* YouTube - https://www.youtube.com/BlenderCommunity\n\n--\n\nPablo Vazquez Links: \n* Instagram - https://instagram.com/pablovazquez.art\n* Twitter - https://twitter.com/pablovazquez_\n* YouTube - https://www.youtube.com/PabloVazquez\n* ArtStation - https://artstation.com/pablovazquez\n\nSupport core Blender development - https://fund.blender.org\n\n#Q&A #BlenderToday #b3d➡️","thumbnails":{"default":{"url":"https://i.ytimg.com/vi/Zoe5P3zBo3Y/default.jpg","width":120,"height":90},"medium":{"url":"https://i.ytimg.com/vi/Zoe5P3zBo3Y/mqdefault.jpg","width":320,"height":180},"high":{"url":"https://i.ytimg.com/vi/Zoe5P3zBo3Y/hqdefault.jpg","width":480,"height":360}},"channelTitle":"Blender","playlistId":"PLa1F2ddGya_87HJ72v_IgKUTNLIXSMfvB","position":26,"resourceId":{"kind":"youtube#video","videoId":"Zoe5P3zBo3Y"},"videoOwnerChannelTitle":"Blender","videoOwnerChannelId":"UCSMOQeBJ2RAnuFungnQOxLg"},"contentDetails":{"videoId":"Zoe5P3zBo3Y","videoPublishedAt":"2020-07-17T16:11:26Z"},"status":{"privacyStatus":"public"}},{"kind":"youtube#playlistItem","etag":"-ASYgSa8SewIu8dsbRIDv2EJcqY","id":"UExhMUYyZGRHeWFfODdISjcydl9JZ0tVVE5MSVhTTWZ2Qi4wQjA4QkVEQ0RFREIzMjFC","snippet":{"publishedAt":"2020-07-12T15:39:04Z","channelId":"UCSMOQeBJ2RAnuFungnQOxLg","title":"Ask Blender Anything! Q&A #111 | Blender.Today Live","description":"Ask away on BlenderToday!\n➡️ Q&A THREAD: https://blender.community/c/today/45fbbc/\n\nAnswering the community's top 20 questions of the week!\n\n==\n\nBlenderToday Links:\n* Chat: https://blender.chat/channel/today\n* Community: http://blender.today\n* Twitter: https://twitter.com/BlenderToday\n* YouTube - https://www.youtube.com/BlenderCommunity\n\n--\n\nPablo Vazquez Links: \n* Instagram - https://instagram.com/pablovazquez.art\n* Twitter - https://twitter.com/pablovazquez_\n* YouTube - https://www.youtube.com/PabloVazquez\n* ArtStation - https://artstation.com/pablovazquez\n\nSupport core Blender development - https://fund.blender.org\n\n#Q&A #BlenderToday #b3d➡️","thumbnails":{"default":{"url":"https://i.ytimg.com/vi/-9GIke1-L-o/default.jpg","width":120,"height":90},"medium":{"url":"https://i.ytimg.com/vi/-9GIke1-L-o/mqdefault.jpg","width":320,"height":180},"high":{"url":"https://i.ytimg.com/vi/-9GIke1-L-o/hqdefault.jpg","width":480,"height":360},"standard":{"url":"https://i.ytimg.com/vi/-9GIke1-L-o/sddefault.jpg","width":640,"height":480},"maxres":{"url":"https://i.ytimg.com/vi/-9GIke1-L-o/maxresdefault.jpg","width":1280,"height":720}},"channelTitle":"Blender","playlistId":"PLa1F2ddGya_87HJ72v_IgKUTNLIXSMfvB","position":27,"resourceId":{"kind":"youtube#video","videoId":"-9GIke1-L-o"},"videoOwnerChannelTitle":"Blender","videoOwnerChannelId":"UCSMOQeBJ2RAnuFungnQOxLg"},"contentDetails":{"videoId":"-9GIke1-L-o","videoPublishedAt":"2020-07-10T16:33:42Z"},"status":{"privacyStatus":"public"}},{"kind":"youtube#playlistItem","etag":"fORCbIaeTytsBpDouKUstwJGzPg","id":"UExhMUYyZGRHeWFfODdISjcydl9JZ0tVVE5MSVhTTWZ2Qi41QTQ4QTIyM0Y1RTBGMUNE","snippet":{"publishedAt":"2020-07-01T17:55:04Z","channelId":"UCSMOQeBJ2RAnuFungnQOxLg","title":"Ask Blender Anything 🤔 BlenderToday Q&A #110","description":"Ask away on BlenderToday! Q&A THREAD: https://blender.community/c/today/f3fbbc/\n\nAnswering the community's top 20 questions of the week!\n\n==\n\nBlenderToday Links:\n* Chat: https://blender.chat/channel/today\n* Community: http://blender.today\n* Twitter: https://twitter.com/BlenderToday\n* YouTube - https://www.youtube.com/BlenderCommunity\n\n--\n\nPablo Vazquez Links: \n* Instagram - https://instagram.com/pablovazquez.art\n* Twitter - https://twitter.com/pablovazquez_\n* YouTube - https://www.youtube.com/PabloVazquez\n* ArtStation - https://artstation.com/pablovazquez\n\nSupport core Blender development - https://fund.blender.org\n\n#Q&A #BlenderToday #b3d","thumbnails":{"default":{"url":"https://i.ytimg.com/vi/YkrSwFKbOzI/default.jpg","width":120,"height":90},"medium":{"url":"https://i.ytimg.com/vi/YkrSwFKbOzI/mqdefault.jpg","width":320,"height":180},"high":{"url":"https://i.ytimg.com/vi/YkrSwFKbOzI/hqdefault.jpg","width":480,"height":360}},"channelTitle":"Blender","playlistId":"PLa1F2ddGya_87HJ72v_IgKUTNLIXSMfvB","position":28,"resourceId":{"kind":"youtube#video","videoId":"YkrSwFKbOzI"},"videoOwnerChannelTitle":"Blender","videoOwnerChannelId":"UCSMOQeBJ2RAnuFungnQOxLg"},"contentDetails":{"videoId":"YkrSwFKbOzI","videoPublishedAt":"2020-07-03T16:15:01Z"},"status":{"privacyStatus":"public"}},{"kind":"youtube#playlistItem","etag":"6kGhgEPbFSCQTjGfZx6DFqBnOM8","id":"UExhMUYyZGRHeWFfODdISjcydl9JZ0tVVE5MSVhTTWZ2Qi43RjdBQTMwNUUwRTA1QkE3","snippet":{"publishedAt":"2020-06-26T14:40:04Z","channelId":"UCSMOQeBJ2RAnuFungnQOxLg","title":"LAST BLENDER TODAY 🥳 BlenderToday #109","description":"This is the last Blender Today as we know it. We'll be restructuring the show starting next week. To go with a bang we have EEVEE updates, Cycles performance, MODELING things wanted for ever, Vertex Painting, overall performance and so much more. Crazy day today. \n\n==\n\nBlenderToday Links:\n* Chat: https://blender.chat/channel/today\n* Community: http://blender.today\n* Twitter: https://twitter.com/BlenderToday\n* YouTube - https://www.youtube.com/BlenderCommunity\n\n--\n\nPablo Vazquez Links: \n* Instagram - https://instagram.com/pablovazquez.art\n* Twitter - https://twitter.com/pablovazquez_\n* YouTube - https://www.youtube.com/PabloVazquez\n* ArtStation - https://artstation.com/pablovazquez\n\nSupport core Blender development - https://fund.blender.org\n\n#Q&A #BlenderToday #b3d","thumbnails":{"default":{"url":"https://i.ytimg.com/vi/U3975RTAckE/default.jpg","width":120,"height":90},"medium":{"url":"https://i.ytimg.com/vi/U3975RTAckE/mqdefault.jpg","width":320,"height":180},"high":{"url":"https://i.ytimg.com/vi/U3975RTAckE/hqdefault.jpg","width":480,"height":360},"standard":{"url":"https://i.ytimg.com/vi/U3975RTAckE/sddefault.jpg","width":640,"height":480},"maxres":{"url":"https://i.ytimg.com/vi/U3975RTAckE/maxresdefault.jpg","width":1280,"height":720}},"channelTitle":"Blender","playlistId":"PLa1F2ddGya_87HJ72v_IgKUTNLIXSMfvB","position":29,"resourceId":{"kind":"youtube#video","videoId":"U3975RTAckE"},"videoOwnerChannelTitle":"Blender","videoOwnerChannelId":"UCSMOQeBJ2RAnuFungnQOxLg"},"contentDetails":{"videoId":"U3975RTAckE","videoPublishedAt":"2020-06-26T17:11:01Z"},"status":{"privacyStatus":"public"}}],"pageInfo":{"totalResults":165,"resultsPerPage":30}}